{
  "version": "0.1.0",
  "description": "Clean manga archives by detecting removable scanlation and ad pages.",
  "homepage": "https://github.com/Qxshio/Trimanga",
  "license": "MIT",
  "architecture": {
    "64bit": {
      "url": "https://github.com/Qxshio/Trimanga/releases/download/v0.1.0/trimanga-windows-x64.zip",
      "hash": "REPLACE_WITH_ZIP_SHA256"
    }
  },
  "bin": "trimanga.exe",
  "checkver": {
    "github": "https://github.com/Qxshio/Trimanga"
  },
  "autoupdate": {
    "architecture": {
      "64bit": {
        "url": "https://github.com/Qxshio/Trimanga/releases/download/v$version/trimanga-windows-x64.zip"
      }
    }
  },
  "notes": "Install Tesseract OCR separately and make sure tesseract.exe is on PATH."
}
